bigchaindb_driver/__init__.py
bigchaindb_driver/connection.py
bigchaindb_driver/crypto.py
bigchaindb_driver/driver.py
bigchaindb_driver/exceptions.py
bigchaindb_driver/offchain.py
bigchaindb_driver/pool.py
bigchaindb_driver/transport.py
bigchaindb_driver/utils.py
bigchaindb_driver-0.5.0a2.dist-info/DESCRIPTION.rst
bigchaindb_driver-0.5.0a2.dist-info/METADATA
bigchaindb_driver-0.5.0a2.dist-info/RECORD
bigchaindb_driver-0.5.0a2.dist-info/WHEEL
bigchaindb_driver-0.5.0a2.dist-info/dependency_links.txt
bigchaindb_driver-0.5.0a2.dist-info/metadata.json
bigchaindb_driver-0.5.0a2.dist-info/top_level.txt
