Metadata-Version: 2.0
Name: bigchaindb-driver
Version: 0.5.0a2
Summary: Python driver for BigchainDB
Home-page: https://github.com/bigchaindb/bigchaindb-driver
Author: BigchainDB
Author-email: dev@bigchaindb.com
License: Apache Software License 2.0
Keywords: bigchaindb_driver
Platform: UNKNOWN
Classifier: Development Status :: 4 - Beta
Classifier: Intended Audience :: Developers
Classifier: License :: OSI Approved :: Apache Software License
Classifier: Natural Language :: English
Classifier: Programming Language :: Python :: 3 :: Only
Classifier: Programming Language :: Python :: 3.5
Classifier: Programming Language :: Python :: 3.6
Requires-Dist: bigchaindb (~=2.0.0a2)
Requires-Dist: requests (>=2.11.0)
Provides-Extra: dev
Requires-Dist: Sphinx (>=1.3.5); extra == 'dev'
Requires-Dist: coverage (>=4.1); extra == 'dev'
Requires-Dist: flake8 (>=2.6.0); extra == 'dev'
Requires-Dist: ipdb; extra == 'dev'
Requires-Dist: ipython; extra == 'dev'
Requires-Dist: matplotlib; extra == 'dev'
Requires-Dist: pre-commit; extra == 'dev'
Requires-Dist: pytest (>=3.0.1); extra == 'dev'
Requires-Dist: pytest-cov; extra == 'dev'
Requires-Dist: pytest-env; extra == 'dev'
Requires-Dist: pytest-sugar; extra == 'dev'
Requires-Dist: pytest-xdist; extra == 'dev'
Requires-Dist: responses (~=0.5.1); extra == 'dev'
Requires-Dist: sphinx-autobuild; extra == 'dev'
Requires-Dist: sphinx-rtd-theme; extra == 'dev'
Requires-Dist: sphinxcontrib-httpdomain; extra == 'dev'
Requires-Dist: sphinxcontrib-napoleon (>=0.4.4); extra == 'dev'
Requires-Dist: tox (>=2.3.1); extra == 'dev'
Provides-Extra: docs
Requires-Dist: Sphinx (>=1.3.5); extra == 'docs'
Requires-Dist: matplotlib; extra == 'docs'
Requires-Dist: sphinx-autobuild; extra == 'docs'
Requires-Dist: sphinx-rtd-theme; extra == 'docs'
Requires-Dist: sphinxcontrib-httpdomain; extra == 'docs'
Requires-Dist: sphinxcontrib-napoleon (>=0.4.4); extra == 'docs'
Provides-Extra: test
Requires-Dist: coverage (>=4.1); extra == 'test'
Requires-Dist: flake8 (>=2.6.0); extra == 'test'
Requires-Dist: pytest (>=3.0.1); extra == 'test'
Requires-Dist: pytest-cov; extra == 'test'
Requires-Dist: pytest-env; extra == 'test'
Requires-Dist: pytest-sugar; extra == 'test'
Requires-Dist: pytest-xdist; extra == 'test'
Requires-Dist: responses (~=0.5.1); extra == 'test'
Requires-Dist: tox (>=2.3.1); extra == 'test'
